word_gen/__init__.py
word_gen/word_gen.py
word_gener-1.2.dist-info/LICENSE
word_gener-1.2.dist-info/METADATA
word_gener-1.2.dist-info/WHEEL
word_gener-1.2.dist-info/top_level.txt
word_gener-1.2.dist-info/RECORD
