Metadata-Version: 2.1
Name: word-gener
Version: 1.2
Summary: generate word file with random data
Home-page: https://github.com/Cherloy/Word_gen
Author: Cherloy
Author-email: sideswipe8@mail.ru
License: MIT
Platform: UNKNOWN
Requires-Python: >=3.6
License-File: LICENSE
